threadless_router
