Metadata-Version: 1.0
Name: rapidsms-threadless-router
Version: 0.1.4
Summary: Threadless router implementation for RapidSMS
Home-page: https://github.com/caktus/rapidsms-threadless-router
Author: Caktus Consulting Group
Author-email: solutions@caktusgroup.com
License: LICENSE.txt
Platform: UNKNOWN
